text_aligner/__init__.py
text_aligner/cli.py
text_aligner/text_aligner.py
text_aligner/utils.py
text_aligner-0.0.3.dist-info/METADATA
text_aligner-0.0.3.dist-info/WHEEL
text_aligner-0.0.3.dist-info/entry_points.txt
text_aligner-0.0.3.dist-info/licenses/LICENSE
text_aligner-0.0.3.dist-info/RECORD
