Metadata-Version: 2.4
Name: text-aligner
Version: 0.0.3
Summary: Text Aligner
Project-URL: Homepage, https://github.com/pengzhendong/text-aligner
Project-URL: Documentation, https://github.com/pengzhendong/text-aligner#readme
Project-URL: BugTracker, https://github.com/pengzhendong/text-aligner/issues
Author-email: Zhendong Peng <pzd17@tsinghua.org.cn>
License:                                  Apache License
License-File: LICENSE
Classifier: Operating System :: OS Independent
Classifier: Programming Language :: Python :: 3
Requires-Python: >=3.8
Requires-Dist: click
Requires-Dist: edit-distance
